.pylintrc
AUTHORS.rst
CONTRIBUTING.rst
HISTORY.rst
LICENSE
MANIFEST.in
README.rst
requirements.txt
setup.cfg
setup.py
tox.ini
datapiper/__init__.py
datapiper/exceptions.py
datapiper/piper.py
datapiper/tasks.py
datapiper/util.py
datapiper.egg-info/PKG-INFO
datapiper.egg-info/SOURCES.txt
datapiper.egg-info/dependency_links.txt
datapiper.egg-info/not-zip-safe
datapiper.egg-info/requires.txt
datapiper.egg-info/top_level.txt
tests/setup.py
tests/test_pipeline.py