Metadata-Version: 1.1
Name: datapiper
Version: 0.1.0
Summary: Simple data processing tool.
Home-page: https://github.com/koodaamo/datapiper
Author: Petri Savolainen
Author-email: petri.savolainen@koodaamo.fi
License: GPLv3
Keywords: datapiper
Platform: UNKNOWN
Classifier: Development Status :: 3 - Alpha
Classifier: Intended Audience :: Developers
Classifier: License :: OSI Approved :: BSD License
Classifier: Natural Language :: English
Classifier: Programming Language :: Python :: 2.7
Classifier: Programming Language :: Python :: 3.5
Classifier: Programming Language :: Python :: 3.6
Classifier: Programming Language :: Python :: 3.7
